<?xml version="1.0" encoding="utf-8"?>
<!DOCTYPE task
  PUBLIC '-//OASIS//DTD DITA Task//EN'
  'dtd1.2/technicalContent/dtd/task.dtd'>
<!-- This file is part of the DITA Open Toolkit project hosted on 
     Sourceforge.net. See the accompanying license.txt file for 
     applicable licenses.-->
<!-- (C) Copyright IBM Corporation 2001, 2005. All Rights Reserved.
 *-->
<task id="changeoil" xml:lang="en-us">
  <title>Maintaining Your Nails</title>
  <shortdesc>By regularly maintaining your nails you will always have healthy, strong nails. </shortdesc>
  <taskbody>
    <context>Maintain your nails once a week.</context>
    <steps>
      <stepsection>To maintain your nails:</stepsection>
      <step>
        <cmd>Remove the old polish.</cmd>
      </step>
      <step>
        <cmd>Soak your cuticles in cuticle remover.</cmd>
      </step>
      <step>
        <cmd>Use a wooden pusher and a cuticle shave to remove old cuticles</cmd>
      </step>
      <step>
        <cmd>File nails using proper form.</cmd>
      </step>
      <step>
        <cmd>Add a protective base coat to your nails.</cmd>
      </step>
      <step>
        <cmd>Soak cuticles in cuticle oil.</cmd>
      </step>
    </steps>
  </taskbody>
  <related-links>
    <link format="dita" href="concept-example.xml" type="concept"/>
    <link format="dita" href="reference-example.xml" type="reference"/>
  </related-links>
</task>
